{
  "tool": "ahrefs",
  "description": "CLI interface for Ahrefs (browser automation)",
  "discovered_at": "2026-06-20T19:38:02Z",
  "total_commands": 14,
  "global_options": [
    {
      "name": "--version",
      "type": "bool",
      "required": false,
      "help": "Show version and exit",
      "short": "-v"
    },
    {
      "name": "--no-cache",
      "type": "bool",
      "required": false,
      "help": "Bypass response cache"
    }
  ],
  "commands": {
    "auth": {
      "help": "Manage Ahrefs authentication",
      "arguments": [],
      "options": [],
      "commands": {
        "login": {
          "help": "Configure authentication credentials. Prompts for required credentials based on the tool's authentication type. For OAuth authorization code flows, opens a browser for user consent.",
          "arguments": [],
          "options": [
            {
              "name": "--profile",
              "type": "TEXT",
              "required": false,
              "help": "Profile name to save credentials to",
              "short": "-p"
            },
            {
              "name": "--force",
              "type": "bool",
              "required": false,
              "help": "Clear existing credentials and re-authenticate",
              "short": "-F"
            }
          ]
        },
        "logout": {
          "help": "Clear stored credentials and browser sessions.",
          "arguments": [],
          "options": [
            {
              "name": "--profile",
              "type": "TEXT",
              "required": false,
              "help": "Profile name to clear credentials from",
              "short": "-p"
            }
          ]
        },
        "profiles": {
          "help": "Manage authentication profiles",
          "arguments": [],
          "options": [],
          "commands": {
            "create": {
              "help": "Create a new profile from .env.example template.",
              "arguments": [
                {
                  "name": "name",
                  "type": "TEXT",
                  "required": true,
                  "help": "Profile name (e.g., staging, production)"
                }
              ],
              "options": []
            },
            "delete": {
              "help": "Delete a profile and its data.",
              "arguments": [
                {
                  "name": "name",
                  "type": "TEXT",
                  "required": true,
                  "help": "Profile name to delete"
                }
              ],
              "options": [
                {
                  "name": "--force",
                  "type": "bool",
                  "required": false,
                  "help": "Skip confirmation",
                  "short": "-F"
                }
              ]
            },
            "get": {
              "help": "Get details for a specific profile.",
              "arguments": [
                {
                  "name": "name",
                  "type": "TEXT",
                  "required": true,
                  "help": "Profile name to get details for"
                }
              ],
              "options": [
                {
                  "name": "--table",
                  "type": "bool",
                  "required": false,
                  "help": "Display as table",
                  "short": "-t"
                }
              ]
            },
            "list": {
              "help": "List all profiles and show which is the default.",
              "arguments": [],
              "options": [
                {
                  "name": "--table",
                  "type": "bool",
                  "required": false,
                  "help": "Display as table",
                  "short": "-t"
                },
                {
                  "name": "--limit",
                  "type": "INTEGER",
                  "required": false,
                  "help": "Maximum number of profiles to return",
                  "short": "-l"
                },
                {
                  "name": "--filter",
                  "type": "TEXT",
                  "required": false,
                  "help": "Filter: field:op:value (e.g., active:eq:True)",
                  "short": "-f"
                },
                {
                  "name": "--properties",
                  "type": "TEXT",
                  "required": false,
                  "help": "Comma-separated list of fields to include",
                  "short": "-p"
                }
              ]
            },
            "remove": {
              "help": "Delete a profile and its data.",
              "arguments": [
                {
                  "name": "name",
                  "type": "TEXT",
                  "required": true,
                  "help": "Profile name to delete"
                }
              ],
              "options": [
                {
                  "name": "--force",
                  "type": "bool",
                  "required": false,
                  "help": "Skip confirmation",
                  "short": "-F"
                }
              ]
            },
            "select": {
              "help": "Activate a profile within its auth type.",
              "arguments": [
                {
                  "name": "name",
                  "type": "TEXT",
                  "required": true,
                  "help": "Profile name to activate within its auth type"
                }
              ],
              "options": []
            }
          }
        },
        "status": {
          "help": "Check authentication status across profiles. Performs a live round-trip for every configured credential type so the report reflects ground truth — not on-disk belief. Saved credentials whose live verification fails are reported as ``authenticated: false`` with the failure reason in ``api_test`` (API/OAuth) or via the live browser check (browser_session).",
          "arguments": [],
          "options": [
            {
              "name": "--profile",
              "type": "TEXT",
              "required": false,
              "help": "Profile name to check (defaults to all profiles)",
              "short": "-p"
            },
            {
              "name": "--table",
              "type": "bool",
              "required": false,
              "help": "Display as table",
              "short": "-t"
            }
          ]
        },
        "test": {
          "help": "Test authentication by verifying credentials work across profiles.",
          "arguments": [],
          "options": [
            {
              "name": "--table",
              "type": "bool",
              "required": false,
              "help": "Display as table",
              "short": "-t"
            },
            {
              "name": "--verbose",
              "type": "bool",
              "required": false,
              "help": "Show detailed checks",
              "short": "-v"
            },
            {
              "name": "--profile",
              "type": "TEXT",
              "required": false,
              "help": "Profile name (defaults to all profiles)",
              "short": "-p"
            }
          ]
        }
      }
    },
    "cache": {
      "help": "Manage response cache",
      "arguments": [],
      "options": [],
      "commands": {
        "clear": {
          "help": "Remove all cached responses. Deletes every file in the cache directory ({storage_dir}/cache/) and reports how many files and bytes were freed.",
          "arguments": [],
          "options": []
        }
      }
    },
    "site-audit": {
      "help": "Site audit operations",
      "arguments": [],
      "options": [
        {
          "name": "--profile",
          "type": "TEXT",
          "required": false,
          "help": "Auth profile name"
        }
      ],
      "commands": {
        "cache": {
          "help": "Manage cached site audit reports. Actions: list  - Show all cached project IDs clear - Clear cached reports Example: ahrefs site-audit cache list ahrefs site-audit cache clear ahrefs site-audit cache clear --project 2185593",
          "arguments": [
            {
              "name": "action",
              "type": "ACTION",
              "required": false,
              "help": "Action: list, clear",
              "default": "list"
            }
          ],
          "options": [
            {
              "name": "--project",
              "type": "INTEGER",
              "required": false,
              "help": "Specific project ID (for clear)",
              "short": "-p"
            },
            {
              "name": "--table",
              "type": "bool",
              "required": false,
              "help": "Display as table",
              "short": "-t"
            },
            {
              "name": "--profile",
              "type": "TEXT",
              "required": false,
              "help": "Auth profile name"
            }
          ]
        },
        "get": {
          "help": "Get complete site audit report for a project. Returns comprehensive audit data including overview metrics, issues by category, orphan pages, redirect chains, and duplicate content. Data is cached locally. Use --refresh to force a fresh fetch. Example: ahrefs site-audit get 2185593 ahrefs site-audit get 2185593 --refresh ahrefs site-audit get 2185593 --table",
          "arguments": [
            {
              "name": "project_id",
              "type": "INTEGER",
              "required": true,
              "help": "Ahrefs project ID"
            }
          ],
          "options": [
            {
              "name": "--refresh",
              "type": "bool",
              "required": false,
              "help": "Force fresh fetch, bypass cache",
              "short": "-r"
            },
            {
              "name": "--table",
              "type": "bool",
              "required": false,
              "help": "Display summary as table",
              "short": "-t"
            },
            {
              "name": "--limit",
              "type": "INTEGER",
              "required": false,
              "help": "Maximum issues per category",
              "short": "-l",
              "default": "100"
            },
            {
              "name": "--filter",
              "type": "TEXT",
              "required": false,
              "help": "Filter: field:op:value (e.g., name:eq:MyItem, status:contains:active)",
              "short": "-f"
            },
            {
              "name": "--properties",
              "type": "TEXT",
              "required": false,
              "help": "Comma-separated list of top-level properties to include",
              "short": "-p"
            },
            {
              "name": "--profile",
              "type": "TEXT",
              "required": false,
              "help": "Auth profile name"
            }
          ]
        },
        "list": {
          "help": "List all site audit crawls for a project. Shows all available crawls/audits with their dates and status. Example: ahrefs site-audit list 2185593 ahrefs site-audit list 2185593 --table ahrefs site-audit list 2185593 --limit 5",
          "arguments": [
            {
              "name": "project_id",
              "type": "INTEGER",
              "required": true,
              "help": "Ahrefs project ID"
            }
          ],
          "options": [
            {
              "name": "--table",
              "type": "bool",
              "required": false,
              "help": "Display as table",
              "short": "-t"
            },
            {
              "name": "--limit",
              "type": "INTEGER",
              "required": false,
              "help": "Maximum number of crawls to return",
              "short": "-l",
              "default": "100"
            },
            {
              "name": "--filter",
              "type": "TEXT",
              "required": false,
              "help": "Filter: field:op:value (e.g., name:eq:MyItem, status:contains:active)",
              "short": "-f"
            },
            {
              "name": "--properties",
              "type": "TEXT",
              "required": false,
              "help": "Comma-separated list of properties to display",
              "short": "-p"
            },
            {
              "name": "--profile",
              "type": "TEXT",
              "required": false,
              "help": "Auth profile name"
            }
          ]
        }
      }
    }
  }
}
